tendril/__init__.py
tendril/apiserver/__init__.py
tendril/apiserver/routers/__init__.py
tendril/apiserver/routers/media_reports.py
tendril/authz/__init__.py
tendril/authz/approvals/__init__.py
tendril/authz/approvals/content.py
tendril/authz/roles/__init__.py
tendril/authz/roles/advertising.py
tendril/authz/roles/content_providers.py
tendril/authz/roles/devices.py
tendril/authz/roles/platform.py
tendril/authz/roles/sxm.py
tendril/common/__init__.py
tendril/common/sxm/__init__.py
tendril/common/sxm/exceptions.py
tendril/common/sxm/formats.py
tendril/config/__init__.py
tendril/config/sxm.py
tendril/config/sxm_media.py
tendril/cron/__init__.py
tendril/cron/jobs/__init__.py
tendril/cron/jobs/device_census.py
tendril/db/__init__.py
tendril/db/controllers/__init__.py
tendril/db/controllers/deviceconfig_sxm.py
tendril/db/models/__init__.py
tendril/db/models/advertising.py
tendril/db/models/content_providers.py
tendril/db/models/deviceconfig_sxm.py
tendril/db/models/devices.py
tendril/db/models/platform.py
tendril/graphs/__init__.py
tendril/graphs/device.py
tendril/graphs/fleet.py
tendril/interests/__init__.py
tendril/interests/advertisement.py
tendril/interests/advertiser.py
tendril/interests/advertising_agency.py
tendril/interests/campaign.py
tendril/interests/carousel_content.py
tendril/interests/content_provider.py
tendril/interests/device.py
tendril/interests/device_content.py
tendril/interests/fleet.py
tendril/interests/fleet_agency.py
tendril/interests/platform.py
tendril/interests/sxm.py
tendril/iotedge/__init__.py
tendril/iotedge/profiles/__init__.py
tendril/iotedge/profiles/sxm.py
tendril/libraries/__init__.py
tendril/libraries/interests/__init__.py
tendril/libraries/interests/content_providers.py
tendril/libraries/interests/platforms.py
tendril/libraries/interests/sxm_advertising.py
tendril/libraries/interests/sxm_devices.py
tendril/monitors/__init__.py
tendril/monitors/sxm_device.py
tendril/monitors/sxm_media.py
tendril/policies/__init__.py
sxm_core-0.4.19.dist-info/LICENSE
sxm_core-0.4.19.dist-info/METADATA
sxm_core-0.4.19.dist-info/WHEEL
sxm_core-0.4.19.dist-info/top_level.txt
sxm_core-0.4.19.dist-info/RECORD
