Metadata-Version: 2.1
Name: sxm-core
Version: 0.4.19
Summary: StarXMedia Primary API Server
Home-page: https://github.com/starxmedia/sxm-core
Author: Chintalagiri Shashank
Author-email: shashank@chintal.in
Project-URL: Documentation, https://sxm-core.readthedocs.io/en/latest
Project-URL: Bug Tracker, https://github.com/starxmedia/sxm-core/issues
Project-URL: Source Repository, https://github.com/starxmedia/sxm-core
Keywords: tendril
Platform: any
Classifier: Development Status :: 4 - Beta
Classifier: License :: OSI Approved :: GNU Affero General Public License v3 or later (AGPLv3+)
Classifier: Natural Language :: English
Classifier: Operating System :: OS Independent
Classifier: Programming Language :: Python
Classifier: Programming Language :: Python :: 3.8
Classifier: Programming Language :: Python :: 3.9
Classifier: Programming Language :: Python :: Implementation :: CPython
Classifier: Programming Language :: Python :: Implementation :: PyPy
Requires-Python: >=3.8
License-File: LICENSE
Requires-Dist: tendril-artefacts
Requires-Dist: tendril-interests >=0.2.4
Requires-Dist: tendril-iotedge
Requires-Dist: tendril-auth
Requires-Dist: tendril-structures-media
Requires-Dist: tendril-structures-imageset
Requires-Dist: wheel
Provides-Extra: build
Requires-Dist: setuptools-scm ; extra == 'build'
Requires-Dist: sphinx ; extra == 'build'
Requires-Dist: sphinx-argparse ; extra == 'build'
Requires-Dist: alabaster ; extra == 'build'
Requires-Dist: pytest ; extra == 'build'
Requires-Dist: pytest-flake8 ; extra == 'build'
Requires-Dist: pytest-cov ; extra == 'build'
Requires-Dist: coveralls[yaml] ; extra == 'build'
Provides-Extra: dev
Requires-Dist: setuptools-scm ; extra == 'dev'
Requires-Dist: sphinx ; extra == 'dev'
Requires-Dist: sphinx-argparse ; extra == 'dev'
Requires-Dist: alabaster ; extra == 'dev'
Requires-Dist: pytest ; extra == 'dev'
Requires-Dist: pytest-flake8 ; extra == 'dev'
Requires-Dist: pytest-cov ; extra == 'dev'
Requires-Dist: coveralls[yaml] ; extra == 'dev'
Provides-Extra: docs
Requires-Dist: setuptools-scm ; extra == 'docs'
Requires-Dist: sphinx ; extra == 'docs'
Requires-Dist: sphinx-argparse ; extra == 'docs'
Requires-Dist: alabaster ; extra == 'docs'
Provides-Extra: publish
Requires-Dist: setuptools-scm ; extra == 'publish'
Requires-Dist: sphinx ; extra == 'publish'
Requires-Dist: sphinx-argparse ; extra == 'publish'
Requires-Dist: alabaster ; extra == 'publish'
Requires-Dist: pytest ; extra == 'publish'
Requires-Dist: pytest-flake8 ; extra == 'publish'
Requires-Dist: pytest-cov ; extra == 'publish'
Requires-Dist: coveralls[yaml] ; extra == 'publish'
Requires-Dist: twine ; extra == 'publish'
Requires-Dist: pygithub ; extra == 'publish'
Provides-Extra: tests
Requires-Dist: setuptools-scm ; extra == 'tests'
Requires-Dist: sphinx ; extra == 'tests'
Requires-Dist: sphinx-argparse ; extra == 'tests'
Requires-Dist: alabaster ; extra == 'tests'
Requires-Dist: pytest ; extra == 'tests'
Requires-Dist: pytest-flake8 ; extra == 'tests'
Requires-Dist: pytest-cov ; extra == 'tests'
Requires-Dist: coveralls[yaml] ; extra == 'tests'
